README.md
setup.cfg
setup.py
fairevaluator/__init__.py
fairevaluator/api_client.py
fairevaluator/configuration.py
fairevaluator/rest.py
fairevaluator.egg-info/PKG-INFO
fairevaluator.egg-info/SOURCES.txt
fairevaluator.egg-info/dependency_links.txt
fairevaluator.egg-info/requires.txt
fairevaluator.egg-info/top_level.txt
fairevaluator/api/__init__.py
fairevaluator/api/create_a_collection_of_maturity_level_tests_api.py
fairevaluator/api/execute_a_maturity_level_evaluation_api.py
fairevaluator/api/register_a_new_maturity_level_test_api.py
fairevaluator/api/retrieve_a_specific_maturity_test_collection_api.py
fairevaluator/api/retrieve_a_specific_maturity_test_description_api.py
fairevaluator/api/retrieve_all_known_maturity_level_tests_api.py
fairevaluator/api/retrieve_an_existing_maturity_level_evaluation_api.py
fairevaluator/api/retrieve_collections_of_maturity_level_tests_api.py
fairevaluator/api/search_maturity_tests_and_collections_by_keyword_api.py
fairevaluator/models/__init__.py
fairevaluator/models/collections.py
fairevaluator/models/collections_array.py
fairevaluator/models/collections_result.py
fairevaluator/models/error_result.py
fairevaluator/models/errorblock.py
fairevaluator/models/evaluate.py
fairevaluator/models/evaluation_result.py
fairevaluator/models/ids.py
fairevaluator/models/metrics.py
fairevaluator/models/metrics_array.py
fairevaluator/models/metrics_list.py
fairevaluator/models/metrics_result.py
fairevaluator/models/search_schema.py
fairevaluator/models/searchinput.py
fairevaluator/models/searchresult.py
test/__init__.py
test/test_collections.py
test/test_collections_array.py
test/test_collections_result.py
test/test_create_a_collection_of_maturity_level_tests_api.py
test/test_error_result.py
test/test_errorblock.py
test/test_evaluate.py
test/test_evaluation_result.py
test/test_execute_a_maturity_level_evaluation_api.py
test/test_ids.py
test/test_metrics.py
test/test_metrics_array.py
test/test_metrics_list.py
test/test_metrics_result.py
test/test_register_a_new_maturity_level_test_api.py
test/test_retrieve_a_specific_maturity_test_collection_api.py
test/test_retrieve_a_specific_maturity_test_description_api.py
