Metadata-Version: 1.0
Name: fairevaluator
Version: 1.0.0
Summary: FAIR Evaluator API
Home-page: https://github.com/FAIRMetrics/Metrics
Author: ['Mark Wilkinson', 'Mario Prieto', 'Pablo Alarc\xc3\xb3n']
Author-email: mark.wilkinson@upm.es
License: UNKNOWN
Keywords: FAIR Evaluator API
Platform: UNKNOWN
